janus_swi/__init__.py
janus_swi/_find_swipl.py
janus_swi/_swipl.cp313-win_amd64.pyd
janus_swi/hash.c
janus_swi/janus.c
janus_swi/janus.pl
janus_swi/janus.py
janus_swi/janus_swi.py
janus_swi/mod_swipl.c
janus_swi-1.5.2.dist-info/LICENSE
janus_swi-1.5.2.dist-info/METADATA
janus_swi-1.5.2.dist-info/WHEEL
janus_swi-1.5.2.dist-info/top_level.txt
janus_swi-1.5.2.dist-info/RECORD
