Metadata-Version: 2.2
Name: janus_swi
Version: 1.5.2
Summary: Janus library to call SWI-Prolog
Home-page: https://github.com/SWI-Prolog/packages-swipy
Author: Jan Wielemaker
Author-email: Jan Wielemaker <jan@swi-prolog.org>
License: BSD-2-Clause
Project-URL: Homepage, https://www.swi-prolog.org
Project-URL: Documentation, https://www.swi-prolog.org/pldoc/package/janus
Project-URL: Repository, https://github.com/SWI-Prolog/packages-swipy.git
Keywords: prolog,logic
Requires-Python: >=3.6
License-File: LICENSE
Dynamic: author
Dynamic: home-page
